qpots/__init__.py
qpots/acquisition.py
qpots/function.py
qpots/model_object.py
qpots/tsemo_runner.py
qpots/TS-EMO/BC_function.py
qpots/TS-EMO/BC_wrapper.m~
qpots/TS-EMO/ChangeLog.md
qpots/TS-EMO/LICENSE
qpots/TS-EMO/README.md
qpots/TS-EMO/TSEMO_Example.m
qpots/TS-EMO/TSEMO_V4.m
qpots/TS-EMO/TSEMO_log.txt
qpots/TS-EMO/TSEMO_options.m
qpots/TS-EMO/TSEMO_run.m
qpots/TS-EMO/TSEMO_run.m~
qpots/TS-EMO/X_20.npy
qpots/TS-EMO/Y_20.npy
qpots/TS-EMO/branincurrin.m
qpots/TS-EMO/carside.m
qpots/TS-EMO/carside.py
qpots/TS-EMO/dh1.m
qpots/TS-EMO/dh1.m~
qpots/TS-EMO/dh1_func.py
qpots/TS-EMO/dh1_func.py~
qpots/TS-EMO/dtlz1.m
qpots/TS-EMO/dtlz1.m~
qpots/TS-EMO/dtlz1_func.py
qpots/TS-EMO/dtlz1_func.py~
qpots/TS-EMO/dtlz3.m
qpots/TS-EMO/dtlz3.m~
qpots/TS-EMO/dtlz3.py
qpots/TS-EMO/dtlz3.py~
qpots/TS-EMO/dtlz7.m
qpots/TS-EMO/dtlz7.m~
qpots/TS-EMO/dtlz7.py
qpots/TS-EMO/dtlz7.py~
qpots/TS-EMO/penicillin.m
qpots/TS-EMO/penicillin_func.py
qpots/TS-EMO/penicllin.m~
qpots/TS-EMO/pennicilin_func.py~
qpots/TS-EMO/startup.m
qpots/TS-EMO/times_20.npy
qpots/TS-EMO/vehicle.m
qpots/TS-EMO/vehiclesafety.py
qpots/TS-EMO/Direct/DIRECT Optimization Algorithm User Guide.pdf
qpots/TS-EMO/Direct/Direct.m
qpots/TS-EMO/Direct/LICENSE
qpots/TS-EMO/Direct/README.md
qpots/TS-EMO/Mex_files/hypervolume/LICENSE
qpots/TS-EMO/Mex_files/hypervolume/README.md
qpots/TS-EMO/Mex_files/hypervolume/hypervolume2D.m
qpots/TS-EMO/Mex_files/hypervolume/hypervolume2D.mexw64
qpots/TS-EMO/Mex_files/hypervolume/hypervolume3D.m
qpots/TS-EMO/Mex_files/hypervolume/hypervolume3D.mexw64
qpots/TS-EMO/Mex_files/invchol/LICENSE
qpots/TS-EMO/Mex_files/invchol/README.md
qpots/TS-EMO/Mex_files/invchol/invChol.m
qpots/TS-EMO/Mex_files/invchol/invChol.mexw64
qpots/TS-EMO/Mex_files/invchol/invChol_mex.c
qpots/TS-EMO/Mex_files/invchol/run_to_compile_and_test.m
qpots/TS-EMO/Mex_files/pareto front/LICENSE
qpots/TS-EMO/Mex_files/pareto front/README.md
qpots/TS-EMO/Mex_files/pareto front/paretofront.m
qpots-1.0.8.dist-info/LICENSE
qpots-1.0.8.dist-info/METADATA
qpots-1.0.8.dist-info/WHEEL
qpots-1.0.8.dist-info/top_level.txt
qpots-1.0.8.dist-info/RECORD
