Metadata-Version: 2.2
Name: qpots
Version: 1.0.8
Summary: A BoTorch wrapper for solving multiobjective optimization problems with an implementation of the qPOTS algorithm.
Author-email: "Kade E. Carlson" <kkc5441@psu.edu>, Ashwin Renganathan <ashwin.renganathan@psu.edu>
License:                     GNU GENERAL PUBLIC LICENSE
Project-URL: Homepage, https://github.com/csdlpsu/qpots
Project-URL: Issues, https://github.com/csdlpsu/qpots/issues
Classifier: Programming Language :: Python :: 3
Classifier: Operating System :: OS Independent
Requires-Python: >=3.10
License-File: LICENSE
Requires-Dist: botorch>=0.12.0
Requires-Dist: torch>=2.4.1
Requires-Dist: gpytorch>=1.13
Requires-Dist: numpy==1.25.2
Requires-Dist: scipy>=1.11.4
Requires-Dist: pymoo>=0.6.1.1
